LICENSE.txt
MANIFEST.in
setup.py
MonzoOAuth/__init__.py
MonzoOAuth.egg-info/PKG-INFO
MonzoOAuth.egg-info/SOURCES.txt
MonzoOAuth.egg-info/dependency_links.txt
MonzoOAuth.egg-info/not-zip-safe
MonzoOAuth.egg-info/requires.txt
MonzoOAuth.egg-info/top_level.txt