Metadata-Version: 1.0
Name: MonzoOAuth
Version: 0.2.0
Summary: An OAuth2 Monzo Client
Home-page: https://github.com/jafacakes2011/MonzoOAuth
Author: Cameron
Author-email: UNKNOWN
License: MIT
Platform: UNKNOWN
